{
    "productInfo": {
        "title": "12\"x8\" PYREX Glass Baking Dish",
        "description": "Made of old-school borosilicate glass, this dish is guaranteed to never crack under heat! No more exploding dishes!",
        "shortDescription": "The biggest baking dishes in the industry",
        "price": 14,
        "img": "",
        "category": "Household and Kitchen Supplies",
        "tags": ["kitchen", "baking", "cooking", "glass", "dish", "hardware", "durable", "borosilicate"]
    },
    "meta" : {
        "createdAt": "",
        "updatedAt": "",
        "createdBy": "Peter Quen"
    }
}